MANIFEST.in
distribute_setup.py
pytest_konira.py
setup.py
pytest_konira.egg-info/PKG-INFO
pytest_konira.egg-info/SOURCES.txt
pytest_konira.egg-info/dependency_links.txt
pytest_konira.egg-info/entry_points.txt
pytest_konira.egg-info/requires.txt
pytest_konira.egg-info/top_level.txt