Metadata-Version: 1.0
Name: pytest-konira
Version: 0.2
Summary: Run Konira DSL tests with py.test
Home-page: UNKNOWN
Author: Alfredo Deza
Author-email: alfredodeza [at] gmail.com
License: MIT
Keywords: test,readable,testrunner,bdd
Platform: UNKNOWN
